{
  "sourceId": "EMAIL-04964",
  "propertyId": "LIE-001",
  "kind": "email",
  "rawPath": "data/emails/2025-07/20250707_165300_EMAIL-04964.eml",
  "rawSha256": "ad941ecf5c82c5412108ababcc7942c4f9872f17b968667ba4a4e870e12384a2",
  "metadata": {
    "headers": {
      "from": "Jasmin Trub <jasmin.trub@outlook.com>",
      "to": "Huber & Partner Immobilienverwaltung GmbH <info@huber-partner-verwaltung.de>",
      "subject": "Wasserschaden Bad",
      "date": "Mon, 07 Jul 2025 16:53:00 -0000",
      "message-id": "<177702011370.22256.17377669709300678691@huber-partner-verwaltung.de>",
      "content-type": "text/plain; charset=\"utf-8\"",
      "content-transfer-encoding": "quoted-printable",
      "mime-version": "1.0"
    },
    "bodyLength": 222
  },
  "normalizedPaths": [
    "workdir/normalized/emails/EMAIL-04964.md"
  ],
  "normalizedSha256": "8e00d5fb012bb31cbe3b28958a38f32964f73402c4bcd008fec717769545468a"
}
