{
  "sourceId": "EMAIL-01831",
  "propertyId": "LIE-001",
  "kind": "email",
  "rawPath": "data/emails/2024-07/20240722_121100_EMAIL-01831.eml",
  "rawSha256": "2c82a65abe0be8f4222e9021714c6a85e49dceee5be7bac24b42a92a00177e2e",
  "metadata": {
    "headers": {
      "from": "Frau Hulda Eckbauer <hulda.eckbauer@t-online.de>",
      "to": "Huber & Partner Immobilienverwaltung GmbH <info@huber-partner-verwaltung.de>",
      "subject": "Modernisierung - Zustimmung",
      "date": "Mon, 22 Jul 2024 12:11:00 -0000",
      "message-id": "<177702011370.22256.14525567791713624614@huber-partner-verwaltung.de>",
      "content-type": "text/plain; charset=\"utf-8\"",
      "content-transfer-encoding": "quoted-printable",
      "mime-version": "1.0"
    },
    "bodyLength": 163
  },
  "normalizedPaths": [
    "workdir/normalized/emails/EMAIL-01831.md"
  ],
  "normalizedSha256": "db1a69746d85a2eb26bbf116ed5697e7f5f19e6bf55fd4abb88fc0711da053c5"
}
