{
  "sourceId": "EMAIL-02578",
  "propertyId": "LIE-001",
  "kind": "email",
  "rawPath": "data/emails/2024-10/20241010_123400_EMAIL-02578.eml",
  "rawSha256": "cb2469425c6943e18700bb2cd7cea92c98c95722534176be08594915f75de577",
  "metadata": {
    "headers": {
      "from": "Thomas Kreuzer <t.kreuzer@huber-partner-verwaltung.de>",
      "to": "Rolf =?utf-8?q?Sch=C3=B6nland?= <rolf.schoenland@allianz-versicherungs-ag.de>",
      "subject": "Re: Terminbestaetigung Wartung",
      "date": "Thu, 10 Oct 2024 12:34:00 -0000",
      "message-id": "<177702011370.22256.18264136098167968178@huber-partner-verwaltung.de>",
      "in-reply-to": "<177702011370.22256.4472675549071552648@huber-partner-verwaltung.de>",
      "references": "<177702011370.22256.4472675549071552648@huber-partner-verwaltung.de>",
      "content-type": "text/plain; charset=\"utf-8\"",
      "content-transfer-encoding": "quoted-printable",
      "mime-version": "1.0"
    },
    "bodyLength": 407
  },
  "normalizedPaths": [
    "workdir/normalized/emails/EMAIL-02578.md"
  ],
  "normalizedSha256": "bbd8406c3023c8f9237b886da483dfebd18a1d973bc53c8829701009fd31c57d"
}
