{
  "sourceId": "EMAIL-02124",
  "propertyId": "LIE-001",
  "kind": "email",
  "rawPath": "data/emails/2024-08/20240822_161700_EMAIL-02124.eml",
  "rawSha256": "3ecd182da2fa08bbccdfd875679e7af98c683d38ebdeb05e8d0d0896e5336bef",
  "metadata": {
    "headers": {
      "from": "Frau =?utf-8?q?D=C3=B6rte?= Kraus <doerte.kraus@gmx.de>",
      "to": "Huber & Partner Immobilienverwaltung GmbH <info@huber-partner-verwaltung.de>",
      "subject": "Modernisierung - Zustimmung",
      "date": "Thu, 22 Aug 2024 16:17:00 -0000",
      "message-id": "<177702011370.22256.256851020627542@huber-partner-verwaltung.de>",
      "content-type": "text/plain; charset=\"utf-8\"",
      "content-transfer-encoding": "quoted-printable",
      "mime-version": "1.0"
    },
    "bodyLength": 161
  },
  "normalizedPaths": [
    "workdir/normalized/emails/EMAIL-02124.md"
  ],
  "normalizedSha256": "e4f9fd309d2874e358a6128439812f8a7878424f40a786baa66184caf6cc4f5b"
}
