{
  "sourceId": "EMAIL-03399",
  "propertyId": "LIE-001",
  "kind": "email",
  "rawPath": "data/emails/2025-01/20250106_162200_EMAIL-03399.eml",
  "rawSha256": "4470a2a38686b844602f30f3e7b2065d4a8a419ba3690c7a44204327e2c5906f",
  "metadata": {
    "headers": {
      "from": "Jacek Weinhold <jacek.weinhold@schornsteinfegermeister-bauer.de>",
      "to": "Huber & Partner Immobilienverwaltung GmbH <info@huber-partner-verwaltung.de>",
      "subject": "Auftragsbestaetigung",
      "date": "Mon, 06 Jan 2025 16:22:00 -0000",
      "message-id": "<177702011370.22256.6424472554358802041@huber-partner-verwaltung.de>",
      "content-type": "text/plain; charset=\"utf-8\"",
      "content-transfer-encoding": "quoted-printable",
      "mime-version": "1.0"
    },
    "bodyLength": 205
  },
  "normalizedPaths": [
    "workdir/normalized/emails/EMAIL-03399.md"
  ],
  "normalizedSha256": "f163080e733a6e32fa39676b05bb317667a63e9f2c0c6cd503bd418c501895e4"
}
