{
  "sourceId": "EMAIL-05211",
  "propertyId": "LIE-001",
  "kind": "email",
  "rawPath": "data/emails/2025-08/20250806_150300_EMAIL-05211.eml",
  "rawSha256": "7fb6b355b9971abdd0405dab336386e10416eea3dfba59dbbb0e0e78ec3e7f0e",
  "metadata": {
    "headers": {
      "from": "Jasmin Trub <jasmin.trub@outlook.com>",
      "to": "Huber & Partner Immobilienverwaltung GmbH <info@huber-partner-verwaltung.de>",
      "subject": "Kuendigung Mietvertrag",
      "date": "Wed, 06 Aug 2025 15:03:00 -0000",
      "message-id": "<177702011370.22256.15606757238961441394@huber-partner-verwaltung.de>",
      "content-type": "text/plain; charset=\"utf-8\"",
      "content-transfer-encoding": "quoted-printable",
      "mime-version": "1.0"
    },
    "bodyLength": 234
  },
  "normalizedPaths": [
    "workdir/normalized/emails/EMAIL-05211.md"
  ],
  "normalizedSha256": "09bd357160480ac60c632e2d997abb91e6aa0a490f5e418441821ed3b6cd7e44"
}
