{
  "sourceId": "EMAIL-01350",
  "propertyId": "LIE-001",
  "kind": "email",
  "rawPath": "data/emails/2024-05/20240530_095500_EMAIL-01350.eml",
  "rawSha256": "c983ee3d80a2e454d636f61080e71b60cb481bd6206e68fcd8e2703b262bd5c7",
  "metadata": {
    "headers": {
      "from": "Herr Harro Bloch <harro.bloch@gmail.com>",
      "to": "Huber & Partner Immobilienverwaltung GmbH <info@huber-partner-verwaltung.de>",
      "subject": "Question about annual statement",
      "date": "Thu, 30 May 2024 09:55:00 -0000",
      "message-id": "<177702011370.22256.3387737554111415990@huber-partner-verwaltung.de>",
      "content-type": "text/plain; charset=\"utf-8\"",
      "content-transfer-encoding": "quoted-printable",
      "mime-version": "1.0"
    },
    "bodyLength": 163
  },
  "normalizedPaths": [
    "workdir/normalized/emails/EMAIL-01350.md"
  ],
  "normalizedSha256": "8fcbb9b4728855cabe1058dbaf00c5c6908be08889365bcadcd241fc9cc37eab"
}
