{
  "sourceId": "EMAIL-06514",
  "propertyId": "LIE-001",
  "kind": "email",
  "rawPath": "data/emails/2025-12/20251229_112200_EMAIL-06514.eml",
  "rawSha256": "6f08d8387cf562b269a0eaa56d3369ce4693aa8f95f0ad11aa7f3635a599c29e",
  "metadata": {
    "headers": {
      "from": "Olga Holsten <olga.holsten@heiztechnik-berlin.de>",
      "to": "Huber & Partner Immobilienverwaltung GmbH <info@huber-partner-verwaltung.de>",
      "subject": "Auftragsbestaetigung",
      "date": "Mon, 29 Dec 2025 11:22:00 -0000",
      "message-id": "<177702011370.22256.13009702535355460828@huber-partner-verwaltung.de>",
      "content-type": "text/plain; charset=\"utf-8\"",
      "content-transfer-encoding": "quoted-printable",
      "mime-version": "1.0"
    },
    "bodyLength": 197
  },
  "normalizedPaths": [
    "workdir/normalized/emails/EMAIL-06514.md"
  ],
  "normalizedSha256": "f100bff320193882e97681a7583bad6f1fa45022d8191e409f8595c17eb92cd1"
}
