{
  "sourceId": "EMAIL-06498",
  "propertyId": "LIE-001",
  "kind": "email",
  "rawPath": "data/emails/2025-12/20251226_200500_EMAIL-06498.eml",
  "rawSha256": "45a5ed82c846bf4a4c03645a12fc639a3d43730f5f7c06f46356b2160aa0299d",
  "metadata": {
    "headers": {
      "from": "Thomas Kreuzer <t.kreuzer@huber-partner-verwaltung.de>",
      "to": "Thomas Kennedy <thomas.kennedy@securelock-systems-ltd.com>",
      "subject": "Re: Maintenance report",
      "date": "Fri, 26 Dec 2025 20:05:00 -0000",
      "message-id": "<177702011370.22256.8326564494902065645@huber-partner-verwaltung.de>",
      "in-reply-to": "<177702011370.22256.13570685273368963608@huber-partner-verwaltung.de>",
      "references": "<177702011370.22256.13570685273368963608@huber-partner-verwaltung.de>",
      "content-type": "text/plain; charset=\"utf-8\"",
      "content-transfer-encoding": "quoted-printable",
      "mime-version": "1.0"
    },
    "bodyLength": 347
  },
  "normalizedPaths": [
    "workdir/normalized/emails/EMAIL-06498.md"
  ],
  "normalizedSha256": "3cd2ab753f4522e8da365bc26c66d2f9f3953b191980356ca1d1059e37016f82"
}
