{
  "sourceId": "EMAIL-02961",
  "propertyId": "LIE-001",
  "kind": "email",
  "rawPath": "data/emails/2024-11/20241121_104300_EMAIL-02961.eml",
  "rawSha256": "9fdfce9cf307ef9bab07aaff1b2b5628fdb068071f83b19066c657c18bf1c388",
  "metadata": {
    "headers": {
      "from": "Falk Trommler <falk.trommler@berliner-wasserbetriebe.de>",
      "to": "Huber & Partner Immobilienverwaltung GmbH <info@huber-partner-verwaltung.de>",
      "subject": "Nachtrag Reparatur",
      "date": "Thu, 21 Nov 2024 10:43:00 -0000",
      "message-id": "<177702011370.22256.17837759022017724058@huber-partner-verwaltung.de>",
      "content-type": "text/plain; charset=\"utf-8\"",
      "content-transfer-encoding": "quoted-printable",
      "mime-version": "1.0"
    },
    "bodyLength": 184
  },
  "normalizedPaths": [
    "workdir/normalized/emails/EMAIL-02961.md"
  ],
  "normalizedSha256": "134740323565e2499db714d6d80ad046913e463f72ae1ba134efabb45141f30e"
}
