{
  "sourceId": "EMAIL-05294",
  "propertyId": "LIE-001",
  "kind": "email",
  "rawPath": "data/emails/2025-08/20250814_131000_EMAIL-05294.eml",
  "rawSha256": "02846303223416754397b34b6f08a88176c0136cb454c96d5ab0a7af77e82a9b",
  "metadata": {
    "headers": {
      "from": "Edelgard Wulf <edelgard.wulf@gmx.de>",
      "to": "Huber & Partner Immobilienverwaltung GmbH <info@huber-partner-verwaltung.de>",
      "subject": "Frage zu Kaution",
      "date": "Thu, 14 Aug 2025 13:10:00 -0000",
      "message-id": "<177702011370.22256.303830024904526636@huber-partner-verwaltung.de>",
      "content-type": "text/plain; charset=\"utf-8\"",
      "content-transfer-encoding": "quoted-printable",
      "mime-version": "1.0"
    },
    "bodyLength": 204
  },
  "normalizedPaths": [
    "workdir/normalized/emails/EMAIL-05294.md"
  ],
  "normalizedSha256": "fc2642087e5b19b6fe6a74993052ff1c08768d8e033b83efa1223885fde62037"
}
