{
  "sourceId": "EMAIL-02648",
  "propertyId": "LIE-001",
  "kind": "email",
  "rawPath": "data/emails/2024-10/20241018_133500_EMAIL-02648.eml",
  "rawSha256": "92195007b3ebbfd82c36876519de93692865e4c01c95d0669d6b87e66129fd49",
  "metadata": {
    "headers": {
      "from": "Berliner Wasserbetriebe <falk.trommler@berliner-wasserbetriebe.de>",
      "to": "Huber & Partner Immobilienverwaltung GmbH <info@huber-partner-verwaltung.de>",
      "subject": "Abschlagsanpassung",
      "date": "Fri, 18 Oct 2024 13:35:00 -0000",
      "message-id": "<177702011370.22256.15620035746788699988@huber-partner-verwaltung.de>",
      "content-type": "text/plain; charset=\"utf-8\"",
      "content-transfer-encoding": "quoted-printable",
      "mime-version": "1.0"
    },
    "bodyLength": 144
  },
  "normalizedPaths": [
    "workdir/normalized/emails/EMAIL-02648.md"
  ],
  "normalizedSha256": "186252de24fc1088abd15f340bfec4d6c358385c7dbd3185cd1eb9c791865dc4"
}
