{
  "sourceId": "EMAIL-02015",
  "propertyId": "LIE-001",
  "kind": "email",
  "rawPath": "data/emails/2024-08/20240811_141900_EMAIL-02015.eml",
  "rawSha256": "310bc7ec9e7b489b9d2204f0311b0b33603ba531b2733bf3cb3fdd60f09ec8fd",
  "metadata": {
    "headers": {
      "from": "Frau Xenia Conradi <xenia.conradi@outlook.com>",
      "to": "Huber & Partner Immobilienverwaltung GmbH <info@huber-partner-verwaltung.de>",
      "subject": "Modernisierung - Zustimmung",
      "date": "Sun, 11 Aug 2024 14:19:00 -0000",
      "message-id": "<177702011370.22256.8572541633140629258@huber-partner-verwaltung.de>",
      "content-type": "text/plain; charset=\"utf-8\"",
      "content-transfer-encoding": "quoted-printable",
      "mime-version": "1.0"
    },
    "bodyLength": 162
  },
  "normalizedPaths": [
    "workdir/normalized/emails/EMAIL-02015.md"
  ],
  "normalizedSha256": "bd0744c77239ac28cbca1d94221877471ab5ab0ebbea6a523650edd0a22ae55b"
}
