{
  "sourceId": "EMAIL-04822",
  "propertyId": "LIE-001",
  "kind": "email",
  "rawPath": "data/emails/2025-06/20250619_223900_EMAIL-04822.eml",
  "rawSha256": "919db751421e342457665b36b7b22ded32f870131371930609c37203955c994d",
  "metadata": {
    "headers": {
      "from": "Thomas Kreuzer <t.kreuzer@huber-partner-verwaltung.de>",
      "to": "Julius Nette <julius.nette@outlook.com>",
      "subject": "Re: Frage zur Nebenkostenabrechnung",
      "date": "Thu, 19 Jun 2025 22:39:00 -0000",
      "message-id": "<177702011370.22256.539314744685783100@huber-partner-verwaltung.de>",
      "in-reply-to": "<177702011370.22256.8360896142612180317@huber-partner-verwaltung.de>",
      "references": "<177702011370.22256.8360896142612180317@huber-partner-verwaltung.de>",
      "content-type": "text/plain; charset=\"utf-8\"",
      "content-transfer-encoding": "quoted-printable",
      "mime-version": "1.0"
    },
    "bodyLength": 565
  },
  "normalizedPaths": [
    "workdir/normalized/emails/EMAIL-04822.md"
  ],
  "normalizedSha256": "86b1ffef03abcbcf91fffaf979b1f15ac54f10b143f437463ad76b1e656ad749"
}
