{
  "sourceId": "EMAIL-05864",
  "propertyId": "LIE-001",
  "kind": "email",
  "rawPath": "data/emails/2025-10/20251013_153500_EMAIL-05864.eml",
  "rawSha256": "c5e398b710b613fa70fbef1e1158dce379fcaee1d48fff32364498d6f3876c25",
  "metadata": {
    "headers": {
      "from": "Herr Oswald =?utf-8?q?Gr=C3=B6ttner?= <oswald.groettner@t-online.de>",
      "to": "Huber & Partner Immobilienverwaltung GmbH <info@huber-partner-verwaltung.de>",
      "subject": "SEV - Monatsauszug",
      "date": "Mon, 13 Oct 2025 15:35:00 -0000",
      "message-id": "<177702011370.22256.16278390171877248935@huber-partner-verwaltung.de>",
      "content-type": "text/plain; charset=\"utf-8\"",
      "content-transfer-encoding": "quoted-printable",
      "mime-version": "1.0"
    },
    "bodyLength": 182
  },
  "normalizedPaths": [
    "workdir/normalized/emails/EMAIL-05864.md"
  ],
  "normalizedSha256": "7e88ae3e4f8faf80904fa24c99c807cd5699c7a267c1fcccc36db29cd85bed3c"
}
