{
  "sourceId": "EMAIL-00009",
  "propertyId": "LIE-001",
  "kind": "email",
  "rawPath": "data/emails/2024-01/20240102_155100_EMAIL-00009.eml",
  "rawSha256": "3b2dd0db1882733612bb2722618f243cc509668f4a9c72616d575f0c0e902aba",
  "metadata": {
    "headers": {
      "from": "Ernst-August Jessel <ernst.august.jessel@sanitaer-schulze.de>",
      "to": "Huber & Partner Immobilienverwaltung GmbH <info@huber-partner-verwaltung.de>",
      "subject": "Mahnung Rechnung RE-2024-7698",
      "date": "Tue, 02 Jan 2024 15:51:00 -0000",
      "message-id": "<177702011370.22256.6166446850406065245@huber-partner-verwaltung.de>",
      "content-type": "text/plain; charset=\"utf-8\"",
      "content-transfer-encoding": "quoted-printable",
      "mime-version": "1.0"
    },
    "bodyLength": 235
  },
  "normalizedPaths": [
    "workdir/normalized/emails/EMAIL-00009.md"
  ],
  "normalizedSha256": "a2cd1ce1d878eb37535dfbf2fe64904dd9efcd742bf71aa9ba62223ac006d02a"
}
