{
  "sourceId": "EMAIL-00314",
  "propertyId": "LIE-001",
  "kind": "email",
  "rawPath": "data/emails/2024-02/20240206_114900_EMAIL-00314.eml",
  "rawSha256": "579ae20d795f61c30e9d74baa5a43ccc41068b4c0bf8a4e359422f135d967564",
  "metadata": {
    "headers": {
      "from": "Allianz Versicherungs-AG <rolf.schoenland@allianz-versicherungs-ag.de>",
      "to": "Huber & Partner Immobilienverwaltung GmbH <info@huber-partner-verwaltung.de>",
      "subject": "Abschlagsanpassung",
      "date": "Tue, 06 Feb 2024 11:49:00 -0000",
      "message-id": "<177702011370.22256.9595166484311270553@huber-partner-verwaltung.de>",
      "content-type": "text/plain; charset=\"utf-8\"",
      "content-transfer-encoding": "quoted-printable",
      "mime-version": "1.0"
    },
    "bodyLength": 145
  },
  "normalizedPaths": [
    "workdir/normalized/emails/EMAIL-00314.md"
  ],
  "normalizedSha256": "1ae8b546c470a29e1cef0ed750c94e92733d4bde8159dca902837d3eb6dfb80f"
}
