{
  "sourceId": "EMAIL-05195",
  "propertyId": "LIE-001",
  "kind": "email",
  "rawPath": "data/emails/2025-08/20250803_151200_EMAIL-05195.eml",
  "rawSha256": "f85f1863d66543706914388778e3943c4dfd0914d8bed9cb6a69e6995c86ccc4",
  "metadata": {
    "headers": {
      "from": "Thomas Kennedy <thomas.kennedy@securelock-systems-ltd.com>",
      "to": "Huber & Partner Immobilienverwaltung GmbH <info@huber-partner-verwaltung.de>",
      "subject": "Quote: Gartenpflege Sommer",
      "date": "Sun, 03 Aug 2025 15:12:00 -0000",
      "message-id": "<177702011370.22256.16675924250460828955@huber-partner-verwaltung.de>",
      "content-type": "text/plain; charset=\"utf-8\"",
      "content-transfer-encoding": "quoted-printable",
      "mime-version": "1.0"
    },
    "bodyLength": 202
  },
  "normalizedPaths": [
    "workdir/normalized/emails/EMAIL-05195.md"
  ],
  "normalizedSha256": "8a6654c43b4e00e8f2711bffe455ae8c2f6a445346642ab393c0fcd675598638"
}
