{
  "sourceId": "EMAIL-01793",
  "propertyId": "LIE-001",
  "kind": "email",
  "rawPath": "data/emails/2024-07/20240717_151800_EMAIL-01793.eml",
  "rawSha256": "180a6d500313889ec0892c3315aa0aefc0333cf919787104345f706ea607683c",
  "metadata": {
    "headers": {
      "from": "Mehdi Faust <mehdi.faust@bsr-berliner-stadtreinigung.de>",
      "to": "Huber & Partner Immobilienverwaltung GmbH <info@huber-partner-verwaltung.de>",
      "subject": "Mahnung Rechnung RE-2024-7344",
      "date": "Wed, 17 Jul 2024 15:18:00 -0000",
      "message-id": "<177702011370.22256.12858098456702125245@huber-partner-verwaltung.de>",
      "content-type": "text/plain; charset=\"utf-8\"",
      "content-transfer-encoding": "quoted-printable",
      "mime-version": "1.0"
    },
    "bodyLength": 233
  },
  "normalizedPaths": [
    "workdir/normalized/emails/EMAIL-01793.md"
  ],
  "normalizedSha256": "100ddde795e022b313d2588a2a4588ce370a94940595e5f8e9bd2a308df3e291"
}
