{
  "sourceId": "EMAIL-01392",
  "propertyId": "LIE-001",
  "kind": "email",
  "rawPath": "data/emails/2024-06/20240603_095900_EMAIL-01392.eml",
  "rawSha256": "9de4b30bb23844108604a45a2ab6a92069b45e054acde611daea7c2940f1fbb3",
  "metadata": {
    "headers": {
      "from": "Mehdi Faust <mehdi.faust@bsr-berliner-stadtreinigung.de>",
      "to": "Huber & Partner Immobilienverwaltung GmbH <info@huber-partner-verwaltung.de>",
      "subject": "Angebot: Sanitaer-Reparatur",
      "date": "Mon, 03 Jun 2024 09:59:00 -0000",
      "message-id": "<177702011370.22256.5943464509395967639@huber-partner-verwaltung.de>",
      "content-type": "text/plain; charset=\"utf-8\"",
      "content-transfer-encoding": "quoted-printable",
      "mime-version": "1.0"
    },
    "bodyLength": 256
  },
  "normalizedPaths": [
    "workdir/normalized/emails/EMAIL-01392.md"
  ],
  "normalizedSha256": "7bc2cbae93af892260ad521e08a1836b92cd44fd417ed7ada901b281a0d219b8"
}
