{
  "sourceId": "EMAIL-01006",
  "propertyId": "LIE-001",
  "kind": "email",
  "rawPath": "data/emails/2024-04/20240421_101400_EMAIL-01006.eml",
  "rawSha256": "d228d4cce36e6b7f0d0401e1e151d17dbd885a0d705b6b8f4e6aa1df18b1da14",
  "metadata": {
    "headers": {
      "from": "Chantal =?utf-8?q?T=C3=A4sche?= <chantal.taesche@posteo.de>",
      "to": "Huber & Partner Immobilienverwaltung GmbH <info@huber-partner-verwaltung.de>",
      "subject": "Mietminderung Ankuendigung",
      "date": "Sun, 21 Apr 2024 10:14:00 -0000",
      "message-id": "<177702011370.22256.16066671681132707202@huber-partner-verwaltung.de>",
      "content-type": "text/plain; charset=\"utf-8\"",
      "content-transfer-encoding": "quoted-printable",
      "mime-version": "1.0"
    },
    "bodyLength": 255
  },
  "normalizedPaths": [
    "workdir/normalized/emails/EMAIL-01006.md"
  ],
  "normalizedSha256": "39ea98f1c28b8df0936f62fa052f7c0a600b75f3f4fc68e4d6253d13a0ac1543"
}
