{
  "sourceId": "EMAIL-01066",
  "propertyId": "LIE-001",
  "kind": "email",
  "rawPath": "data/emails/2024-04/20240428_172700_EMAIL-01066.eml",
  "rawSha256": "398d31b46aca8554ef5d301f0f1086231b6ea65f4d890f150caa1ee8d16ef32a",
  "metadata": {
    "headers": {
      "from": "Herr Marcus Dowerg <marcus.dowerg@outlook.com>",
      "to": "Huber & Partner Immobilienverwaltung GmbH <info@huber-partner-verwaltung.de>",
      "subject": "Sonderumlage - Einspruch",
      "date": "Sun, 28 Apr 2024 17:27:00 -0000",
      "message-id": "<177702011370.22256.15932205311770015417@huber-partner-verwaltung.de>",
      "content-type": "text/plain; charset=\"utf-8\"",
      "content-transfer-encoding": "quoted-printable",
      "mime-version": "1.0"
    },
    "bodyLength": 226
  },
  "normalizedPaths": [
    "workdir/normalized/emails/EMAIL-01066.md"
  ],
  "normalizedSha256": "826f0d22d3b0c889bd5a2dcff22c94724972688dc65c933fc3fd935a148c16ad"
}
