{
  "sourceId": "EMAIL-02945",
  "propertyId": "LIE-001",
  "kind": "email",
  "rawPath": "data/emails/2024-11/20241118_124400_EMAIL-02945.eml",
  "rawSha256": "e68892f51afc63e9f168ce2f9fb6b8b3d3e9a78f816c36c379c13603c8395edc",
  "metadata": {
    "headers": {
      "from": "Marliese Hermann <marliese.hermann@posteo.de>",
      "to": "Huber & Partner Immobilienverwaltung GmbH <info@huber-partner-verwaltung.de>",
      "subject": "Wohnungsuebergabe",
      "date": "Mon, 18 Nov 2024 12:44:00 -0000",
      "message-id": "<177702011370.22256.9074267069587384340@huber-partner-verwaltung.de>",
      "content-type": "text/plain; charset=\"utf-8\"",
      "content-transfer-encoding": "quoted-printable",
      "mime-version": "1.0"
    },
    "bodyLength": 161
  },
  "normalizedPaths": [
    "workdir/normalized/emails/EMAIL-02945.md"
  ],
  "normalizedSha256": "cb5052e2cd42eaa68da1887fd8520010f64b695858f7f2f7d30e9d0d865944bb"
}
