{
  "sourceId": "EMAIL-03401",
  "propertyId": "LIE-001",
  "kind": "email",
  "rawPath": "data/emails/2025-01/20250107_091400_EMAIL-03401.eml",
  "rawSha256": "5d780fe757e2e54ddc47dbe110734e84422544ddb1b4453c382b88e5b2ea3c55",
  "metadata": {
    "headers": {
      "from": "Herr Marcus Dowerg <marcus.dowerg@outlook.com>",
      "to": "Huber & Partner Immobilienverwaltung GmbH <info@huber-partner-verwaltung.de>",
      "subject": "Mieterwechsel in GE 37",
      "date": "Tue, 07 Jan 2025 09:14:00 -0000",
      "message-id": "<177702011370.22256.13225515115677124168@huber-partner-verwaltung.de>",
      "content-type": "text/plain; charset=\"utf-8\"",
      "content-transfer-encoding": "quoted-printable",
      "mime-version": "1.0"
    },
    "bodyLength": 187
  },
  "normalizedPaths": [
    "workdir/normalized/emails/EMAIL-03401.md"
  ],
  "normalizedSha256": "828e8e6b8d315f32f065c5beb16c56b7e602aa810ee8801ea96e1543c10745cb"
}
