{
  "sourceId": "EMAIL-02691",
  "propertyId": "LIE-001",
  "kind": "email",
  "rawPath": "data/emails/2024-10/20241023_000500_EMAIL-02691.eml",
  "rawSha256": "ae5b3d0d23981b7f8b1d253500454bbce7f578126b9682750404d1b0304b7f5d",
  "metadata": {
    "headers": {
      "from": "Sabine Huber <sabine.huber@huber-partner-verwaltung.de>",
      "to": "Louise Ladeck <louise.ladeck@outlook.com>",
      "subject": "Re: Mietminderung Ankuendigung",
      "date": "Wed, 23 Oct 2024 00:05:00 -0000",
      "message-id": "<177702011370.22256.6389314975191354939@huber-partner-verwaltung.de>",
      "in-reply-to": "<177702011370.22256.2377642920648591461@huber-partner-verwaltung.de>",
      "references": "<177702011370.22256.2377642920648591461@huber-partner-verwaltung.de>",
      "content-type": "text/plain; charset=\"utf-8\"",
      "content-transfer-encoding": "quoted-printable",
      "mime-version": "1.0"
    },
    "bodyLength": 505
  },
  "normalizedPaths": [
    "workdir/normalized/emails/EMAIL-02691.md"
  ],
  "normalizedSha256": "a53b33fc5eb6396d4dc0238ed100df94fd4878c9c9749547f6aace4999e832ba"
}
