{
  "sourceId": "INV-00166",
  "propertyId": "LIE-001",
  "kind": "invoice_pdf",
  "rawPath": "data/rechnungen/2025-09/20250922_DL-002_INV-00166.pdf",
  "rawSha256": "7538cc4ca0e617d174eae9018d754d6c84aa04d8c396e10e00363f955da29ec2",
  "metadata": {
    "filename": "20250922_DL-002_INV-00166.pdf",
    "date": "2025-09-22",
    "contractorId": "DL-002",
    "invoiceId": "INV-00166",
    "flags": {
      "duplicateMarker": false,
      "fakeMarker": false
    },
    "invoiceNumber": "R20250078",
    "customerNumber": "KN-45103 Rechnungsnr.: R20250078 Datum: 22.09.2025",
    "invoiceDate": "22.09.2025",
    "netAmount": "185.00",
    "vatAmount": "35.15",
    "grossAmount": "220.15",
    "iban": "DE13 3704 0044 9368 9980 94",
    "title": "Kundennr.: KN-45103 Rechnungsnr.: R20250078 Datum: 22.09.2025",
    "pageCount": 1,
    "textLength": 559,
    "normalizerVersion": 4
  },
  "normalizedPaths": [
    "workdir/normalized/invoices/INV-00166.md"
  ],
  "normalizedSha256": "500b7db278293df9fab2bacabb61e769e19f1d7c455ce0e2c9a925c9120e8789"
}
