{
  "sourceId": "INV-00082",
  "propertyId": "LIE-001",
  "kind": "invoice_pdf",
  "rawPath": "data/rechnungen/2024-11/20241127_DL-013_INV-00082.pdf",
  "rawSha256": "841cc0b55dd4978edf82c5fc97fcb170910390f3ae9bf2b9790421de7ac5a644",
  "metadata": {
    "filename": "20241127_DL-013_INV-00082.pdf",
    "date": "2024-11-27",
    "contractorId": "DL-013",
    "invoiceId": "INV-00082",
    "flags": {
      "duplicateMarker": false,
      "fakeMarker": false
    },
    "invoiceNumber": "RE-2024-0123",
    "invoiceDate": "27.11.2024",
    "netAmount": "55.00",
    "vatAmount": "10.45",
    "grossAmount": "65.45",
    "title": "Rechnungsnr.: RE-2024-0123",
    "pageCount": 1,
    "textLength": 634,
    "normalizerVersion": 4
  },
  "normalizedPaths": [
    "workdir/normalized/invoices/INV-00082.md"
  ],
  "normalizedSha256": "b9b2cba6dfc63146be55f9e01d91761b244c91c5924aba12e6db0d3e82a1f725"
}
