{
  "sourceId": "INV-00151",
  "propertyId": "LIE-001",
  "kind": "invoice_pdf",
  "rawPath": "data/rechnungen/2025-07/20250728_DL-001_INV-00151.pdf",
  "rawSha256": "9a50b33b982be2bc83b61bb7fecf6188c3c6d8f1589665a188f85fc0f74d6a52",
  "metadata": {
    "filename": "20250728_DL-001_INV-00151.pdf",
    "date": "2025-07-28",
    "contractorId": "DL-001",
    "invoiceId": "INV-00151",
    "flags": {
      "duplicateMarker": false,
      "fakeMarker": false
    },
    "invoiceNumber": "R20250019",
    "invoiceDate": "28.07.2025",
    "netAmount": "886.20",
    "vatAmount": "168.38",
    "grossAmount": "1054.58",
    "title": "RECHNUNG",
    "pageCount": 1,
    "textLength": 1042,
    "normalizerVersion": 4
  },
  "normalizedPaths": [
    "workdir/normalized/invoices/INV-00151.md"
  ],
  "normalizedSha256": "c5e8e4f334db68e32ea86f92a40f502198141523491451201fca10ef3ee69fd4"
}
